telebot_plugins/__init__.py
telebot_plugins-0.1.4.dist-info/METADATA
telebot_plugins-0.1.4.dist-info/WHEEL
telebot_plugins-0.1.4.dist-info/top_level.txt
telebot_plugins-0.1.4.dist-info/RECORD
