Metadata-Version: 2.4
Name: telebot-plugins
Version: 0.1.4
Summary: A simple plugin system for pyTelegramBotAPI (telebot)
Home-page: https://github.com/x7007x/TelebotPlugins
Author: Ahmed Negm
Author-email: A7medNegm.x@gmail.com
Classifier: Programming Language :: Python :: 3
Classifier: License :: OSI Approved :: MIT License
Classifier: Operating System :: OS Independent
Requires-Python: >=3.6
Requires-Dist: pyTelegramBotAPI>=4.0.0
Dynamic: author
Dynamic: author-email
Dynamic: classifier
Dynamic: description
Dynamic: description-content-type
Dynamic: home-page
Dynamic: requires-dist
Dynamic: requires-python
Dynamic: summary
